python/__Init__.py
python/api_client.py
python/config.py
python/contacts.py
python/lists.py
python/tags.py
python_demo_suthish-0.1.2.dist-info/METADATA
python_demo_suthish-0.1.2.dist-info/WHEEL
python_demo_suthish-0.1.2.dist-info/top_level.txt
python_demo_suthish-0.1.2.dist-info/RECORD
