Metadata-Version: 2.2
Name: python_demo_suthish
Version: 0.1.2
Requires-Dist: requests>=2.25.0
Dynamic: requires-dist
